README.md
setup.py
snos/__init__.py
snos/helpers.py
snos/snos
snos.egg-info/PKG-INFO
snos.egg-info/SOURCES.txt
snos.egg-info/dependency_links.txt
snos.egg-info/top_level.txt