Metadata-Version: 1.1
Name: snos
Version: 0.0.45
Summary: Command line tool for keeping notes simple way.
Home-page: https://github.com/ferdielik/snos
Author: Ferdi Elik
Author-email: elik.ferdi@gmail.com
License: MIT
Platform: UNKNOWN
Classifier: Development Status :: 4 - Beta
Classifier: Intended Audience :: System Administrators
Classifier: License :: OSI Approved :: Apache Software License
Classifier: Programming Language :: Python :: 3
